{
	"array": [
		{
			"client_msg_id": "3d014070-5282-486f-9c00-0e434f76db94",
			"type": "message",
			"user": "U01QNJ7PWRX",
			"text": "&lt;PwC(프라이스워터하우스쿠퍼스컨설팅, 삼일회계법인의 파트너사)의 Financial Services 본부에서 인턴을 모집합니다.&gt;\n\n안녕하세요\n\nPwC(프라이스워터하우스쿠퍼스컨설팅, 삼일회계법인의 파트너사)의 Financial Services 본부에서 인턴을 모집합니다.\n\n●    업무내용 : 금융 빅데이터 분석, 리서치, 기타 업무지원 등\n●    위치 : 삼성역 인근\n●    기간 : 2월 중순부터 약 6개월간 Full-time 근무\n●    지원자 필수요건 :\n(1) 데이터 분석가/컨설턴트로써 경력을 쌓고자 하는 분\n(2) Python/R/SQL 을 이용한 데이터 분석 경험이 있거나 관련 수업을 듣고 학점을 이수하신 분\n(3) 고객 실무자, 컨설턴트, 분석가 및 개발자들과 원활한 소통을 할 수 있고, 타인을 배려하는 태도를 가진 분\n●    우대요건 : 빅데이터/경영학/통계학/산업공학 등 관련 전공자, 기 인턴 경험자\n●    지원방법 : 한글 이력서와 커버레터 (약 500자 정도의 간략한 지원동기 및 자기소개)를 메일 (<mailto:jinhyung.yang@pwc.com|jinhyung.yang@pwc.com>)로 제출\n●    모집기간 : 2023년 2월 17일(금)까지\n●    대면 면접 후 채용을 결정하며, 지원자가 많을 경우 조기 마감될 수 있습니다.\n\n실제 데이터를 이용한 모델링 및 컨설팅 업무를 경험할 수 있는 귀한 기회이니, 미래 데이터 분석가 및 컨설턴트 여러분의 많은 지원 바랍니다.",
			"ts": "1675919109.244759",
			"team": "T01QA5S537V",
			"replace_original": false,
			"delete_original": false,
			"metadata": {
				"event_type": "",
				"event_payload": null
			},
			"blocks": [
				{
					"type": "rich_text",
					"block_id": "vWA",
					"elements": [
						{
							"type": "rich_text_section",
							"elements": [
								{
									"type": "text",
									"text": "<PwC(프라이스워터하우스쿠퍼스컨설팅, 삼일회계법인의 파트너사)의 Financial Services 본부에서 인턴을 모집합니다.>\n\n안녕하세요\n\nPwC(프라이스워터하우스쿠퍼스컨설팅, 삼일회계법인의 파트너사)의 Financial Services 본부에서 인턴을 모집합니다.\n\n●    업무내용 : 금융 빅데이터 분석, 리서치, 기타 업무지원 등\n●    위치 : 삼성역 인근\n●    기간 : 2월 중순부터 약 6개월간 Full-time 근무\n●    지원자 필수요건 :\n(1) 데이터 분석가/컨설턴트로써 경력을 쌓고자 하는 분\n(2) Python/R/SQL 을 이용한 데이터 분석 경험이 있거나 관련 수업을 듣고 학점을 이수하신 분\n(3) 고객 실무자, 컨설턴트, 분석가 및 개발자들과 원활한 소통을 할 수 있고, 타인을 배려하는 태도를 가진 분\n●    우대요건 : 빅데이터/경영학/통계학/산업공학 등 관련 전공자, 기 인턴 경험자\n●    지원방법 : 한글 이력서와 커버레터 (약 500자 정도의 간략한 지원동기 및 자기소개)를 메일 ("
								},
								{
									"type": "link",
									"url": "mailto:jinhyung.yang@pwc.com",
									"text": "jinhyung.yang@pwc.com"
								},
								{
									"type": "text",
									"text": ")로 제출\n●    모집기간 : 2023년 2월 17일(금)까지\n●    대면 면접 후 채용을 결정하며, 지원자가 많을 경우 조기 마감될 수 있습니다.\n\n실제 데이터를 이용한 모델링 및 컨설팅 업무를 경험할 수 있는 귀한 기회이니, 미래 데이터 분석가 및 컨설턴트 여러분의 많은 지원 바랍니다."
								}
							]
						}
					]
				}
			],
			"user_team": "T01QA5S537V",
			"source_team": "T01QA5S537V",
			"user_profile": {
				"avatar_hash": "",
				"image_72": "https://secure.gravatar.com/avatar/f81e0af3f0233b60131463158e3f434c.jpg?s=72&d=https%3A%2F%2Fa.slack-edge.com%2Fdf10d%2Fimg%2Favatars%2Fava_0019-72.png",
				"first_name": "GSDS행정실",
				"real_name": "GSDS행정실",
				"display_name": "GSDS행정실",
				"team": "T01QA5S537V",
				"name": "snu.gsds",
				"is_restricted": false,
				"is_ultra_restricted": false
			},
			"reply_users_count": 0,
			"reply_users": null
		}
	]
}