{
	"array": [
		{
			"client_msg_id": "400bb1d2-3963-4ab9-8025-e8512e6fba8a",
			"type": "message",
			"user": "U01QNJ7PWRX",
			"text": "&lt;2023년「사회봉사활동 체험수기」공모 안내&gt;\n\n우리 사회 각 분야에서 헌신적인 봉사활동으로 나눔과 배려의 정신을 실천하는 학생들의 체험수기를 공모하여 포상하고자 2023년 사회봉사활동 체험수기 공모 계획을 알려드리니, 관심있는 학생들은 참여하여 주시기 바랍니다.\n  가. 공모대상: 학생들의 사회봉사활동 체험수기\n  나. 공모기간: 2023. 9. 18.(월)까지\n  다. 신청방법: 제출 서류 양식 및 봉사 증빙서류를 작성하여 담당자 이메일(<mailto:song03@snu.ac.kr|song03@snu.ac.kr>)로 제출\n  라. 선발인원: 약간 명(최우수, 우수, 장려)\n  마. 시상내용: 상장 및 부상(학업장려금), 학적부 등재\n    ※ 2023. 10. 13.(금) 개교기념식에 시상 예정",
			"ts": "1693810309.045809",
			"files": [
				{
					"id": "F05QD538C15",
					"created": 1693810304,
					"timestamp": 1693810304,
					"name": "붙임 2. 제출서류 묶음.zip",
					"title": "붙임 2. 제출서류 묶음.zip",
					"mimetype": "application/zip",
					"image_exif_rotation": 0,
					"filetype": "zip",
					"pretty_type": "Zip",
					"user": "U01QNJ7PWRX",
					"mode": "hosted",
					"editable": false,
					"is_external": false,
					"external_type": "",
					"size": 57037,
					"url": "",
					"url_download": "",
					"url_private": "attachments/F05QD538C15-붙임 2. 제출서류 묶음.zip",
					"url_private_download": "attachments/F05QD538C15-붙임 2. 제출서류 묶음.zip",
					"original_h": 0,
					"original_w": 0,
					"thumb_64": "",
					"thumb_80": "",
					"thumb_160": "",
					"thumb_360": "",
					"thumb_360_gif": "",
					"thumb_360_w": 0,
					"thumb_360_h": 0,
					"thumb_480": "",
					"thumb_480_w": 0,
					"thumb_480_h": 0,
					"thumb_720": "",
					"thumb_720_w": 0,
					"thumb_720_h": 0,
					"thumb_960": "",
					"thumb_960_w": 0,
					"thumb_960_h": 0,
					"thumb_1024": "",
					"thumb_1024_w": 0,
					"thumb_1024_h": 0,
					"permalink": "https://snugsds.slack.com/files/U01QNJ7PWRX/F05QD538C15/_______2.____________________.zip",
					"permalink_public": "https://slack-files.com/T01QA5S537V-F05QD538C15-eeb10c6836",
					"edit_link": "",
					"preview": "",
					"preview_highlight": "",
					"lines": 0,
					"lines_more": 0,
					"is_public": true,
					"public_url_shared": false,
					"channels": null,
					"groups": null,
					"ims": null,
					"initial_comment": {},
					"comments_count": 0,
					"num_stars": 0,
					"is_starred": false,
					"shares": {
						"public": null,
						"private": null
					}
				},
				{
					"id": "F05QQPB22H3",
					"created": 1693810306,
					"timestamp": 1693810306,
					"name": "붙임 1. 2023년 사회봉사활동 체험수기 공모 계획_최종.hwp",
					"title": "붙임 1. 2023년 사회봉사활동 체험수기 공모 계획_최종.hwp",
					"mimetype": "application/octet-stream",
					"image_exif_rotation": 0,
					"filetype": "binary",
					"pretty_type": "이진",
					"user": "U01QNJ7PWRX",
					"mode": "hosted",
					"editable": false,
					"is_external": false,
					"external_type": "",
					"size": 70656,
					"url": "",
					"url_download": "",
					"url_private": "attachments/F05QQPB22H3-붙임 1. 2023년 사회봉사활동 체험수기 공모 계획_최종.hwp",
					"url_private_download": "attachments/F05QQPB22H3-붙임 1. 2023년 사회봉사활동 체험수기 공모 계획_최종.hwp",
					"original_h": 0,
					"original_w": 0,
					"thumb_64": "",
					"thumb_80": "",
					"thumb_160": "",
					"thumb_360": "",
					"thumb_360_gif": "",
					"thumb_360_w": 0,
					"thumb_360_h": 0,
					"thumb_480": "",
					"thumb_480_w": 0,
					"thumb_480_h": 0,
					"thumb_720": "",
					"thumb_720_w": 0,
					"thumb_720_h": 0,
					"thumb_960": "",
					"thumb_960_w": 0,
					"thumb_960_h": 0,
					"thumb_1024": "",
					"thumb_1024_w": 0,
					"thumb_1024_h": 0,
					"permalink": "https://snugsds.slack.com/files/U01QNJ7PWRX/F05QQPB22H3/_______1._2023________________________________________________________.hwp",
					"permalink_public": "https://slack-files.com/T01QA5S537V-F05QQPB22H3-3b91915d9c",
					"edit_link": "",
					"preview": "",
					"preview_highlight": "",
					"lines": 0,
					"lines_more": 0,
					"is_public": true,
					"public_url_shared": false,
					"channels": null,
					"groups": null,
					"ims": null,
					"initial_comment": {},
					"comments_count": 0,
					"num_stars": 0,
					"is_starred": false,
					"shares": {
						"public": null,
						"private": null
					}
				}
			],
			"replace_original": false,
			"delete_original": false,
			"metadata": {
				"event_type": "",
				"event_payload": null
			},
			"blocks": [
				{
					"type": "rich_text",
					"block_id": "meGf",
					"elements": [
						{
							"type": "rich_text_section",
							"elements": [
								{
									"type": "text",
									"text": "<2023년「사회봉사활동 체험수기」공모 안내>\n\n우리 사회 각 분야에서 헌신적인 봉사활동으로 나눔과 배려의 정신을 실천하는 학생들의 체험수기를 공모하여 포상하고자 2023년 사회봉사활동 체험수기 공모 계획을 알려드리니, 관심있는 학생들은 참여하여 주시기 바랍니다.\n  가. 공모대상: 학생들의 사회봉사활동 체험수기\n  나. 공모기간: 2023. 9. 18.(월)까지\n  다. 신청방법: 제출 서류 양식 및 봉사 증빙서류를 작성하여 담당자 이메일("
								},
								{
									"type": "link",
									"url": "mailto:song03@snu.ac.kr",
									"text": "song03@snu.ac.kr"
								},
								{
									"type": "text",
									"text": ")로 제출\n  라. 선발인원: 약간 명(최우수, 우수, 장려)\n  마. 시상내용: 상장 및 부상(학업장려금), 학적부 등재\n    ※ 2023. 10. 13.(금) 개교기념식에 시상 예정"
								}
							]
						}
					]
				}
			],
			"user_team": "",
			"source_team": "",
			"user_profile": {
				"avatar_hash": "",
				"image_72": "https://secure.gravatar.com/avatar/f81e0af3f0233b60131463158e3f434c.jpg?s=72&d=https%3A%2F%2Fa.slack-edge.com%2Fdf10d%2Fimg%2Favatars%2Fava_0019-72.png",
				"first_name": "GSDS행정실",
				"real_name": "GSDS행정실",
				"display_name": "GSDS행정실",
				"team": "T01QA5S537V",
				"name": "snu.gsds",
				"is_restricted": false,
				"is_ultra_restricted": false
			},
			"reply_users_count": 0,
			"reply_users": null
		}
	]
}