[
  {
    "client_msg_id": "46eeb0ad-88d5-4109-a7b1-5600220c4c7a",
    "type": "message",
    "user": "U01QNJ7PWRX",
    "text": "「2023 학생 창업유망팀 300」 안내\n\n교육부에서 전국 학생들의 창업에 대한 도전의식을 고취하기 위해 개최하는 「2023 학생 창업유망팀 300」을안내하오니 관심 있는 학생 여러분께서는 참여하시기 바랍니다.\nㅇ 운영주체 : (주최) 교육부(주관) 한국연구재단, 한국청년기업가정신재단\nㅇ 참가자격:  전국 초·중·고교, 학교 밖 청소년 및 대학(원) 소속 *학생(휴학생/수료생 포함)*으로 구성된 예비창업팀 또는 3년 이내(‘20.1.26 이후) 창업팀 *(3인 ~ 5인 구성)*\nㅇ 신청방법 : 창업유망팀300 홈페이지(\u003chttp://www.u300.kr|www.u300.kr\u003e)에서 온라인 신청\nㅇ문의사항 : 한국청년기업가정신재단 대학창업팀(\u003ctel:0221562295|02-2156-2295\u003e, 2359)\n※  모집대상 및 선발규모, 접수 마감일자, 연계대회 등 세부내용을 첨부 공고문 참고",
    "ts": "1680745831.435139",
    "files": [
      {
        "id": "F052RB30PDW",
        "created": 1680745731,
        "timestamp": 1680745731,
        "name": "2023 학생 창업유망팀 300 공고문.hwpx",
        "title": "2023 학생 창업유망팀 300 공고문.hwpx",
        "mimetype": "application/octet-stream",
        "image_exif_rotation": 0,
        "filetype": "binary",
        "pretty_type": "이진",
        "user": "U01QNJ7PWRX",
        "mode": "hosted",
        "editable": false,
        "is_external": false,
        "external_type": "",
        "size": 1688561,
        "url": "",
        "url_download": "",
        "url_private": "attachments/F052RB30PDW-2023 학생 창업유망팀 300 공고문.hwpx",
        "url_private_download": "attachments/F052RB30PDW-2023 학생 창업유망팀 300 공고문.hwpx",
        "original_h": 0,
        "original_w": 0,
        "thumb_64": "",
        "thumb_80": "",
        "thumb_160": "",
        "thumb_360": "",
        "thumb_360_gif": "",
        "thumb_360_w": 0,
        "thumb_360_h": 0,
        "thumb_480": "",
        "thumb_480_w": 0,
        "thumb_480_h": 0,
        "thumb_720": "",
        "thumb_720_w": 0,
        "thumb_720_h": 0,
        "thumb_960": "",
        "thumb_960_w": 0,
        "thumb_960_h": 0,
        "thumb_1024": "",
        "thumb_1024_w": 0,
        "thumb_1024_h": 0,
        "permalink": "https://snugsds.slack.com/files/U01QNJ7PWRX/F052RB30PDW/2023________________________300__________.hwpx",
        "permalink_public": "https://slack-files.com/T01QA5S537V-F052RB30PDW-d4c5271f46",
        "edit_link": "",
        "preview": "",
        "preview_highlight": "",
        "lines": 0,
        "lines_more": 0,
        "is_public": true,
        "public_url_shared": false,
        "channels": null,
        "groups": null,
        "ims": null,
        "initial_comment": {},
        "comments_count": 0,
        "num_stars": 0,
        "is_starred": false,
        "shares": {
          "public": null,
          "private": null
        }
      },
      {
        "id": "F0521LETHT4",
        "created": 1680745814,
        "timestamp": 1680745814,
        "name": "2023 학생 창업유망팀 300 포스터.png",
        "title": "2023 학생 창업유망팀 300 포스터.png",
        "mimetype": "image/png",
        "image_exif_rotation": 0,
        "filetype": "png",
        "pretty_type": "PNG",
        "user": "U01QNJ7PWRX",
        "mode": "hosted",
        "editable": false,
        "is_external": false,
        "external_type": "",
        "size": 3426146,
        "url": "",
        "url_download": "",
        "url_private": "attachments/F0521LETHT4-2023 학생 창업유망팀 300 포스터.png",
        "url_private_download": "attachments/F0521LETHT4-2023 학생 창업유망팀 300 포스터.png",
        "original_h": 4335,
        "original_w": 3077,
        "thumb_64": "https://files.slack.com/files-tmb/T01QA5S537V-F0521LETHT4-91d2c6f842/2023________________________300___________64.png",
        "thumb_80": "https://files.slack.com/files-tmb/T01QA5S537V-F0521LETHT4-91d2c6f842/2023________________________300___________80.png",
        "thumb_160": "https://files.slack.com/files-tmb/T01QA5S537V-F0521LETHT4-91d2c6f842/2023________________________300___________160.png",
        "thumb_360": "https://files.slack.com/files-tmb/T01QA5S537V-F0521LETHT4-91d2c6f842/2023________________________300___________360.png",
        "thumb_360_gif": "",
        "thumb_360_w": 256,
        "thumb_360_h": 360,
        "thumb_480": "https://files.slack.com/files-tmb/T01QA5S537V-F0521LETHT4-91d2c6f842/2023________________________300___________480.png",
        "thumb_480_w": 341,
        "thumb_480_h": 480,
        "thumb_720": "https://files.slack.com/files-tmb/T01QA5S537V-F0521LETHT4-91d2c6f842/2023________________________300___________720.png",
        "thumb_720_w": 511,
        "thumb_720_h": 720,
        "thumb_960": "https://files.slack.com/files-tmb/T01QA5S537V-F0521LETHT4-91d2c6f842/2023________________________300___________960.png",
        "thumb_960_w": 681,
        "thumb_960_h": 960,
        "thumb_1024": "https://files.slack.com/files-tmb/T01QA5S537V-F0521LETHT4-91d2c6f842/2023________________________300___________1024.png",
        "thumb_1024_w": 727,
        "thumb_1024_h": 1024,
        "permalink": "https://snugsds.slack.com/files/U01QNJ7PWRX/F0521LETHT4/2023________________________300__________.png",
        "permalink_public": "https://slack-files.com/T01QA5S537V-F0521LETHT4-91a6533625",
        "edit_link": "",
        "preview": "",
        "preview_highlight": "",
        "lines": 0,
        "lines_more": 0,
        "is_public": true,
        "public_url_shared": false,
        "channels": null,
        "groups": null,
        "ims": null,
        "initial_comment": {},
        "comments_count": 0,
        "num_stars": 0,
        "is_starred": false,
        "shares": {
          "public": null,
          "private": null
        }
      }
    ],
    "replace_original": false,
    "delete_original": false,
    "metadata": {
      "event_type": "",
      "event_payload": null
    },
    "blocks": [
      {
        "type": "rich_text",
        "block_id": "kvmXw",
        "elements": [
          {
            "type": "rich_text_section",
            "elements": [
              {
                "type": "text",
                "text": "「2023 학생 창업유망팀 300」 안내\n\n교육부에서 전국 학생들의 창업에 대한 도전의식을 고취하기 위해 개최하는 「2023 학생 창업유망팀 300」을안내하오니 관심 있는 학생 여러분께서는 참여하시기 바랍니다.\nㅇ 운영주체 : (주최) 교육부(주관) 한국연구재단, 한국청년기업가정신재단\nㅇ 참가자격:  전국 초·중·고교, 학교 밖 청소년 및 대학(원) 소속 "
              },
              {
                "type": "text",
                "text": "학생(휴학생/수료생 포함)",
                "style": {
                  "bold": true
                }
              },
              {
                "type": "text",
                "text": "으로 구성된 예비창업팀 또는 3년 이내(‘20.1.26 이후) 창업팀 "
              },
              {
                "type": "text",
                "text": "(3인 ~ 5인 구성)",
                "style": {
                  "bold": true
                }
              },
              {
                "type": "text",
                "text": "\nㅇ 신청방법 : 창업유망팀300 홈페이지("
              },
              {
                "type": "link",
                "url": "http://www.u300.kr",
                "text": "www.u300.kr"
              },
              {
                "type": "text",
                "text": ")에서 온라인 신청\nㅇ문의사항 : 한국청년기업가정신재단 대학창업팀("
              },
              {
                "type": "link",
                "url": "tel:0221562295",
                "text": "02-2156-2295"
              },
              {
                "type": "text",
                "text": ", 2359)\n※  모집대상 및 선발규모, 접수 마감일자, 연계대회 등 세부내용을 첨부 공고문 참고"
              }
            ]
          }
        ]
      }
    ],
    "user_team": "",
    "source_team": "",
    "user_profile": {
      "avatar_hash": "",
      "image_72": "https://secure.gravatar.com/avatar/f81e0af3f0233b60131463158e3f434c.jpg?s=72\u0026d=https%3A%2F%2Fa.slack-edge.com%2Fdf10d%2Fimg%2Favatars%2Fava_0019-72.png",
      "first_name": "GSDS행정실",
      "real_name": "GSDS행정실",
      "display_name": "GSDS행정실",
      "team": "T01QA5S537V",
      "name": "snu.gsds",
      "is_restricted": false,
      "is_ultra_restricted": false
    },
    "reply_users_count": 0,
    "reply_users": null
  }
]
